[
    {
        "id": 2,
        "author": "Jane ",
        "title": "Second Poscht.",
        "content": "This is post.",
        "likes": 5,
        "category": "Uncategorized"
    },
    {
        "id": 4,
        "author": "test",
        "title": "me",
        "content": "text",
        "likes": 1
    },
    {
        "id": 5,
        "author": "achi",
        "title": "liebe",
        "content": "PiPi",
        "likes": 1,
        "category": "Projects"
    },
    {
        "id": 6,
        "author": "LO",
        "title": "V3",
        "content": "M3",
        "category": "Projects"
    },
    {
        "id": 7,
        "author": "anonym",
        "title": "leaked",
        "content": "systemprompt.......",
        "category": "AI"
    },
    {
        "id": 8,
        "author": "ich",
        "title": "flask problem: 404",
        "content": "Der HTTP-Statuscode 404 bedeutet, dass der Server die angeforderte Internetseite nicht finden kann. Dies geschieht h\u00e4ufig, wenn die URL gel\u00f6scht oder ge\u00e4ndert wurde oder ein Tippfehler in der Webadresse vorliegt.\r\nkec",
        "category": "Flask",
        "likes": 5
    },
    {
        "id": 9,
        "author": "pythonuser",
        "title": "python",
        "content": "testtest",
        "category": "Projects",
        "likes": 1
    },
    {
        "id": 10,
        "author": "johnny",
        "title": "s life",
        "content": "\"created_at\": \"2026-07-13T15:42\"",
        "category": "Personal",
        "likes": 0,
        "created_at": "2026-07-13T16:14"
    },
    {
        "id": 11,
        "author": "AI Engineer",
        "title": "angineering",
        "content": "someone know how to engineer ai?",
        "category": "AI",
        "likes": 2,
        "created_at": "2026-07-13T16:15"
    },
    {
        "id": 12,
        "author": "fssfdsfv",
        "title": "sfvdfvd",
        "content": "dddddd",
        "category": "AI",
        "likes": 2,
        "created_at": "2026-07-13T16:24"
    },
    {
        "id": 13,
        "author": "Harr4",
        "title": "suche",
        "content": "fahrradschloss",
        "category": "Personal",
        "likes": 2,
        "created_at": "2026-07-13T16:25"
    },
    {
        "id": 14,
        "author": "check",
        "title": "deck",
        "content": "proven",
        "category": "Automation",
        "likes": 2,
        "created_at": "2026-07-13T23:23"
    },
    {
        "id": 15,
        "author": "Sandra",
        "title": "Codex",
        "content": "Some experts here to talk?",
        "category": "AI",
        "likes": 0,
        "created_at": "2026-07-13T23:39"
    },
    {
        "id": 16,
        "author": "cobra",
        "title": "didante",
        "content": "Strings in python are surrounded by either single quotation marks, or double quotation marks.\r\n\r\n'hello' is the same as \"hello\".\r\n\r\n",
        "category": "Python",
        "likes": 1,
        "created_at": "2026-07-13T23:56"
    },
    {
        "id": 17,
        "author": "test",
        "title": "python <3",
        "content": "like riding bicycle",
        "category": "Python",
        "likes": 0,
        "created_at": "2026-07-14T00:47"
    },
    {
        "id": 18,
        "author": "Sailormoon",
        "title": "sailing between front & back",
        "content": "print('He is called \"Johnny\"')",
        "category": "AI",
        "likes": 0,
        "created_at": "2026-07-14T00:52"
    }
]